bep20
