Metadata-Version: 2.1
Name: bep20
Version: 1.0.2
Summary: Python package that models the methods for tokens following the BEP-20 token standard on the Binance Smart chain.
Home-page: https://github.com/hschickdevs/Python-BEP20-Token
Author: Harrison Schick
Author-email: hschickdevs@gmail.com
License: UNKNOWN
Platform: UNKNOWN
License-File: LICENSE
